alephmarcreader/__init__.py
alephmarcreader/abstractalephmarcreader.py
alephmarcreader/alephmarc21reader.py
alephmarcreader/alephmarcxmlreader.py
alephmarcreader/alephxreader.py
alephmarcreader-1.1.0.dist-info/LICENSE
alephmarcreader-1.1.0.dist-info/METADATA
alephmarcreader-1.1.0.dist-info/WHEEL
alephmarcreader-1.1.0.dist-info/top_level.txt
alephmarcreader-1.1.0.dist-info/RECORD
