Metadata-Version: 2.1
Name: alephmarcreader
Version: 1.1.0
Summary: A package to read Marc data obtained from Aleph, the catalogue of the library of the University of Basel
Home-page: https://github.com/dhlab-basel/alephmarcreader.git
Author: Tobias Schweizer, Digital Humanities Lab, University of Basel; Balduin Landolt, University of Basel
Author-email: t.schweizer@unibas.ch
License: UNKNOWN
Platform: UNKNOWN
Classifier: Programming Language :: Python :: 3
Classifier: License :: OSI Approved :: GNU Affero General Public License v3
Classifier: Operating System :: OS Independent
